{
  "timestamp": 1537824996104,
  "webhookEvent": "jira:issue_updated",
  "issue_event_type_name": "issue_generic",
  "user": {
    "self": "https://stanfordits.atlassian.net/rest/api/2/user?username=pookmish",
    "name": "pookmish",
    "key": "pookmish",
    "accountId": "557058:ff72a71b-af40-484a-911f-749f71bd353d",
    "emailAddress": "pookmish@stanford.edu",
    "avatarUrls": {
      "48x48": "https://avatar-cdn.atlassian.com/b757876904286e7710a6fa1cc34ff4e4?s=48&d=https%3A%2F%2Fstanfordits.atlassian.net%2Fsecure%2Fuseravatar%3FavatarId%3D10162%26noRedirect%3Dtrue",
      "24x24": "https://avatar-cdn.atlassian.com/b757876904286e7710a6fa1cc34ff4e4?s=24&d=https%3A%2F%2Fstanfordits.atlassian.net%2Fsecure%2Fuseravatar%3Fsize%3Dsmall%26avatarId%3D10162%26noRedirect%3Dtrue",
      "16x16": "https://avatar-cdn.atlassian.com/b757876904286e7710a6fa1cc34ff4e4?s=16&d=https%3A%2F%2Fstanfordits.atlassian.net%2Fsecure%2Fuseravatar%3Fsize%3Dxsmall%26avatarId%3D10162%26noRedirect%3Dtrue",
      "32x32": "https://avatar-cdn.atlassian.com/b757876904286e7710a6fa1cc34ff4e4?s=32&d=https%3A%2F%2Fstanfordits.atlassian.net%2Fsecure%2Fuseravatar%3Fsize%3Dmedium%26avatarId%3D10162%26noRedirect%3Dtrue"
    },
    "displayName": "Michael Decker",
    "active": true,
    "timeZone": "America/Los_Angeles"
  },
  "issue": {
    "id": "64017",
    "self": "https://stanfordits.atlassian.net/rest/api/2/issue/64017",
    "key": "ARCH-387",
    "fields": {
      "issuetype": {
        "self": "https://stanfordits.atlassian.net/rest/api/2/issuetype/1",
        "id": "1",
        "description": "A problem which impairs or prevents the functions of the product.",
        "iconUrl": "https://stanfordits.atlassian.net/secure/viewavatar?size=xsmall&avatarId=10543&avatarType=issuetype",
        "name": "Bug",
        "subtask": false,
        "avatarId": 10543
      },
      "timespent": null,
      "project": {
        "self": "https://stanfordits.atlassian.net/rest/api/2/project/17810",
        "id": "17810",
        "key": "ARCH",
        "name": "Archaeology Center D8 Site",
        "projectTypeKey": "software",
        "avatarUrls": {
          "48x48": "https://stanfordits.atlassian.net/secure/projectavatar?avatarId=12043",
          "24x24": "https://stanfordits.atlassian.net/secure/projectavatar?size=small&avatarId=12043",
          "16x16": "https://stanfordits.atlassian.net/secure/projectavatar?size=xsmall&avatarId=12043",
          "32x32": "https://stanfordits.atlassian.net/secure/projectavatar?size=medium&avatarId=12043"
        },
        "projectCategory": {
          "self": "https://stanfordits.atlassian.net/rest/api/2/projectCategory/10030",
          "id": "10030",
          "description": "Stanford Web Services Projects",
          "name": "70 SWS"
        }
      },
      "fixVersions": [],
      "customfield_10231": [],
      "customfield_10232": null,
      "aggregatetimespent": null,
      "resolution": null,
      "customfield_10630": null,
      "customfield_11400": null,
      "customfield_10631": null,
      "resolutiondate": null,
      "workratio": -1,
      "lastViewed": "2018-09-24T14:16:30.479-0700",
      "watches": {
        "self": "https://stanfordits.atlassian.net/rest/api/2/issue/ARCH-387/watchers",
        "watchCount": 1,
        "isWatching": true
      },
      "created": "2018-09-24T14:09:33.611-0700",
      "customfield_11230": "{}",
      "priority": {
        "self": "https://stanfordits.atlassian.net/rest/api/2/priority/4",
        "iconUrl": "https://stanfordits.atlassian.net/images/icons/priorities/major.svg",
        "name": "4 - Must Fix - Low",
        "id": "4"
      },
      "labels": [],
      "customfield_11700": null,
      "customfield_11702": null,
      "customfield_11701": null,
      "aggregatetimeoriginalestimate": null,
      "timeestimate": null,
      "customfield_11703": null,
      "versions": [],
      "customfield_11706": null,
      "customfield_11705": [],
      "issuelinks": [],
      "assignee": null,
      "updated": "2018-09-24T14:36:36.074-0700",
      "status": {
        "self": "https://stanfordits.atlassian.net/rest/api/2/status/3",
        "description": "This issue is being actively worked on at the moment by the assignee.",
        "iconUrl": "https://stanfordits.atlassian.net/images/icons/statuses/inprogress.png",
        "name": "In Progress",
        "id": "3",
        "statusCategory": {
          "self": "https://stanfordits.atlassian.net/rest/api/2/statuscategory/4",
          "id": 4,
          "key": "indeterminate",
          "colorName": "yellow",
          "name": "In Progress"
        }
      },
      "components": [],
      "timeoriginalestimate": null,
      "description": "Test Bugherd Connection stuff\n\nRequester: Stanford WebServices\nURL: \nBrowser: \nBrowser size: \nBrowser size: ",
      "customfield_10130": null,
      "customfield_10012": null,
      "customfield_11300": {
        "isEditable": false,
        "nonEditableReason": {
          "reason": "PLUGIN_LICENSE_ERROR",
          "message": "Portfolio for Jira must be licensed for the team field to be available."
        }
      },
      "customfield_10530": null,
      "customfield_10531": null,
      "customfield_11500": null,
      "timetracking": {},
      "customfield_10532": null,
      "customfield_10730": null,
      "security": null,
      "aggregatetimeestimate": null,
      "attachment": [],
      "summary": "BUGHERD-2: Test Bugherd Connection stuff",
      "creator": {
        "self": "https://stanfordits.atlassian.net/rest/api/2/user?username=pookmish",
        "name": "pookmish",
        "key": "pookmish",
        "accountId": "557058:ff72a71b-af40-484a-911f-749f71bd353d",
        "emailAddress": "pookmish@stanford.edu",
        "avatarUrls": {
          "48x48": "https://avatar-cdn.atlassian.com/b757876904286e7710a6fa1cc34ff4e4?s=48&d=https%3A%2F%2Fstanfordits.atlassian.net%2Fsecure%2Fuseravatar%3FavatarId%3D10162%26noRedirect%3Dtrue",
          "24x24": "https://avatar-cdn.atlassian.com/b757876904286e7710a6fa1cc34ff4e4?s=24&d=https%3A%2F%2Fstanfordits.atlassian.net%2Fsecure%2Fuseravatar%3Fsize%3Dsmall%26avatarId%3D10162%26noRedirect%3Dtrue",
          "16x16": "https://avatar-cdn.atlassian.com/b757876904286e7710a6fa1cc34ff4e4?s=16&d=https%3A%2F%2Fstanfordits.atlassian.net%2Fsecure%2Fuseravatar%3Fsize%3Dxsmall%26avatarId%3D10162%26noRedirect%3Dtrue",
          "32x32": "https://avatar-cdn.atlassian.com/b757876904286e7710a6fa1cc34ff4e4?s=32&d=https%3A%2F%2Fstanfordits.atlassian.net%2Fsecure%2Fuseravatar%3Fsize%3Dmedium%26avatarId%3D10162%26noRedirect%3Dtrue"
        },
        "displayName": "Michael Decker",
        "active": true,
        "timeZone": "America/Los_Angeles"
      },
      "subtasks": [],
      "customfield_11130": {
        "hasEpicLinkFieldDependency": false,
        "showField": false,
        "nonEditableReason": {
          "reason": "PLUGIN_LICENSE_ERROR",
          "message": "Portfolio for Jira must be licensed for the Parent Link to be available."
        }
      },
      "reporter": null,
      "aggregateprogress": {
        "progress": 0,
        "total": 0
      },
      "customfield_10000": null,
      "customfield_10002": null,
      "customfield_10003": null,
      "customfield_10236": "1|i01qzf:",
      "customfield_11600": null,
      "customfield_10237": null,
      "customfield_10238": "2018-09-24T14:14:09.647-0700",
      "environment": null,
      "duedate": null,
      "progress": {
        "progress": 0,
        "total": 0
      },
      "votes": {
        "self": "https://stanfordits.atlassian.net/rest/api/2/issue/ARCH-387/votes",
        "votes": 0,
        "hasVoted": false
      }
    }
  },
  "changelog": {
    "id": "280923",
    "items": [
      {
        "field": "status",
        "fieldtype": "jira",
        "fieldId": "status",
        "from": "10301",
        "fromString": "To Do",
        "to": "3",
        "toString": "In Progress"
      }
    ]
  }
}